stopywatch/Classes.py
stopywatch/__init__.py
stopywatch-1.0.2.dist-info/LICENSE
stopywatch-1.0.2.dist-info/METADATA
stopywatch-1.0.2.dist-info/WHEEL
stopywatch-1.0.2.dist-info/top_level.txt
stopywatch-1.0.2.dist-info/RECORD
