Metadata-Version: 2.1
Name: stopywatch
Version: 1.0.2
Summary: Simple Python 3 Stopwatch
Home-page: https://gitlab.com/jsanchezd/stopywatch
Author: Jesus Alejandro Sanchez Davila
Author-email: jsanchez.consultant@gmail.com
License: UNKNOWN
Platform: UNKNOWN
Classifier: Programming Language :: Python :: 3
Classifier: License :: OSI Approved :: MIT License
Classifier: Operating System :: OS Independent
Requires-Python: >=3.6
License-File: LICENSE
